nonebot_adapter_onebot_pretender/__init__.py
nonebot_adapter_onebot_pretender/data/__init__.py
nonebot_adapter_onebot_pretender/data/ob11_msg.py
nonebot_adapter_onebot_pretender/patch_handle_event.py
nonebot_adapter_onebot_pretender/store.py
nonebot_adapter_onebot_pretender/v11/__init__.py
nonebot_adapter_onebot_pretender/v11/adapter.py
nonebot_adapter_onebot_pretender/v11/factory.py
nonebot_adapter_onebot_pretender/v11/impl/__init__.py
nonebot_adapter_onebot_pretender/v11/impl/red/__init__.py
nonebot_adapter_onebot_pretender/v11/pretender.py
nonebot_adapter_onebot_pretender/webapi/__init__.py
nonebot_adapter_onebot_pretender/webapi/red.py
nonebot_adapter_onebot_pretender-0.1.1.dist-info/LICENSE
nonebot_adapter_onebot_pretender-0.1.1.dist-info/METADATA
nonebot_adapter_onebot_pretender-0.1.1.dist-info/WHEEL
nonebot_adapter_onebot_pretender-0.1.1.dist-info/RECORD
