Metadata-Version: 2.1
Name: nonebot-adapter-onebot-pretender
Version: 0.1.1
Summary: 
Home-page: https://github.com/ssttkkl/nonebot-adapter-onebot-pretender
License: MIT
Author: ssttkkl
Author-email: huang.wen.long@hotmail.com
Requires-Python: >=3.8,<4.0
Classifier: License :: OSI Approved :: MIT License
Classifier: Programming Language :: Python :: 3
Classifier: Programming Language :: Python :: 3.8
Classifier: Programming Language :: Python :: 3.9
Classifier: Programming Language :: Python :: 3.10
Classifier: Programming Language :: Python :: 3.11
Requires-Dist: nonebot-adapter-onebot (>=2.3.0,<3.0.0)
Requires-Dist: nonebot-plugin-datastore (>=1.1.2,<2.0.0)
Requires-Dist: nonebot2 (>=2.1.0,<3.0.0)
Requires-Dist: unqlite (>=0.9.6,<0.10.0)
Project-URL: Repository, https://github.com/ssttkkl/nonebot-adapter-onebot-pretender
